geography/__init__.py
geography/admin.py
geography/api.py
geography/apps.py
geography/autocomplete.py
geography/forms.py
geography/search_indexes.py
geography/string_utils.py
geography/urls.py
geography/locale/fr/LC_MESSAGES/django.mo
geography/locale/fr/LC_MESSAGES/django.po
geography/management/__init__.py
geography/management/commands/__init__.py
geography/management/commands/load_geo.py
geography/management/commands/load_timezones.py
geography/models/__init__.py
geography/models/address.py
geography/models/city.py
geography/models/conurbation.py
geography/models/country.py
geography/models/department.py
geography/models/region.py
geography/models/timezone.py
geography/templates/search/search.html
geography/templates/search/indexes/geography/city_text.txt
geography/tests/__init__.py
geography/tests/test_address_model.py
django_geonames_api-0.8.8.dist-info/METADATA
django_geonames_api-0.8.8.dist-info/WHEEL
django_geonames_api-0.8.8.dist-info/top_level.txt
django_geonames_api-0.8.8.dist-info/RECORD
